otsuwinhdlr/__init__.py
otsuwinhdlr/classes.py
otsuwinhdlr-2022.11.30.dist-info/METADATA
otsuwinhdlr-2022.11.30.dist-info/WHEEL
otsuwinhdlr-2022.11.30.dist-info/top_level.txt
otsuwinhdlr-2022.11.30.dist-info/RECORD
