Metadata-Version: 2.1
Name: otsuwinhdlr
Version: 2022.11.30
Summary: ウィンドウやエクスプローラのハンドル取得、操作を補助します。
Home-page: https://github.com/Otsuhachi/OtsuWinHdlr
Author: Otsuhachi
Author-email: agequodagis.tufuiegoeris@gmail.com
Requires-Dist: otsutil
Requires-Dist: otsuvalidator
Requires-Dist: otsuwinAPI
